events/__init__.py
events/apps.py
events/data.py
events/models.py
events/urls.py
events/management/__init__.py
events/management/commands/__init__.py
events/management/commands/consume_coupon_code_request_events.py
events/settings/__init__.py
events/settings/common.py
events/settings/devstack.py
events/settings/production.py
events/templates/events/base.html
ecommerce_plugin_events-0.1.2.dist-info/LICENSE
ecommerce_plugin_events-0.1.2.dist-info/LICENSE.txt
ecommerce_plugin_events-0.1.2.dist-info/METADATA
ecommerce_plugin_events-0.1.2.dist-info/WHEEL
ecommerce_plugin_events-0.1.2.dist-info/entry_points.txt
ecommerce_plugin_events-0.1.2.dist-info/top_level.txt
ecommerce_plugin_events-0.1.2.dist-info/RECORD
