Metadata-Version: 2.1
Name: ecommerce-plugin-events
Version: 0.1.2
Summary: Plugin to handle events consumed by ecommerce
Home-page: https://github.com/edx/ecommerce-plugin-events
Author: edX
Author-email: oscm@edx.org
License: AGPL 3.0
Keywords: Python edx
Platform: UNKNOWN
Classifier: Development Status :: 3 - Alpha
Classifier: Framework :: Django
Classifier: Framework :: Django :: 2.2
Classifier: Intended Audience :: Developers
Classifier: License :: OSI Approved :: GNU Affero General Public License v3 or later (AGPLv3+)
Classifier: Natural Language :: English
Classifier: Programming Language :: Python :: 3
Classifier: Programming Language :: Python :: 3.8
Requires-Python: >=3.8
Requires-Dist: Django
Requires-Dist: confluent-kafka
Requires-Dist: edx-django-utils
Requires-Dist: fastavro
Requires-Dist: openedx-events
Requires-Dist: requests
Requires-Dist: setuptools
